DIYables_Pico_Keypad/DIYables_Pico_Keypad.py
DIYables_Pico_Keypad/__init__.py
DIYables_Pico_Keypad-0.1.1.dist-info/LICENSE
DIYables_Pico_Keypad-0.1.1.dist-info/METADATA
DIYables_Pico_Keypad-0.1.1.dist-info/WHEEL
DIYables_Pico_Keypad-0.1.1.dist-info/top_level.txt
DIYables_Pico_Keypad-0.1.1.dist-info/RECORD
